zappa/__init__.py
zappa/asynchronous.py
zappa/cli.py
zappa/core.py
zappa/handler.py
zappa/letsencrypt.py
zappa/middleware.py
zappa/policies.py
zappa/utilities.py
zappa/wsgi.py
zappa/ext/__init__.py
zappa/ext/django_zappa.py
zappa/policies/assume_policy.json
zappa/policies/attach_policy.json
zappa-0.61.4.dist-info/licenses/LICENSE
zappa-0.61.4.dist-info/METADATA
zappa-0.61.4.dist-info/WHEEL
zappa-0.61.4.dist-info/entry_points.txt
zappa-0.61.4.dist-info/top_level.txt
zappa-0.61.4.dist-info/RECORD
