Metadata-Version: 2.4
Name: zappa
Version: 0.61.4
Summary: Server-less Python Web Services for AWS Lambda and API Gateway
Home-page: https://github.com/zappa/Zappa
Author: Rich Jones
Author-email: rich@openwatch.net
License: MIT License
Classifier: Environment :: Console
Classifier: License :: OSI Approved :: Apache Software License
Classifier: Operating System :: OS Independent
Classifier: Programming Language :: Python
Classifier: Programming Language :: Python :: 3.9
Classifier: Programming Language :: Python :: 3.10
Classifier: Programming Language :: Python :: 3.11
Classifier: Programming Language :: Python :: 3.12
Classifier: Programming Language :: Python :: 3.13
Classifier: Programming Language :: Python :: 3.14
Classifier: Framework :: Django
Classifier: Framework :: Django :: 4.2
Classifier: Framework :: Django :: 5.2
Classifier: Topic :: Internet :: WWW/HTTP
Classifier: Topic :: Internet :: WWW/HTTP :: Dynamic Content
Requires-Python: >=3.9
License-File: LICENSE
Requires-Dist: argcomplete
Requires-Dist: boto3>=1.17.28
Requires-Dist: durationpy
Requires-Dist: hjson
Requires-Dist: jmespath
Requires-Dist: pip>=24.0.0
Requires-Dist: placebo<0.10
Requires-Dist: python-dateutil
Requires-Dist: python-slugify
Requires-Dist: pyyaml
Requires-Dist: requests>=2.32.0
Requires-Dist: toml
Requires-Dist: tqdm>=4.66.3
Requires-Dist: troposphere>=3.0
Requires-Dist: werkzeug
Requires-Dist: wheel
Requires-Dist: setuptools<80.0.0
Dynamic: author
Dynamic: author-email
Dynamic: classifier
Dynamic: description
Dynamic: description-content-type
Dynamic: home-page
Dynamic: license
Dynamic: license-file
Dynamic: requires-dist
Dynamic: requires-python
Dynamic: summary
